affirm/__init__.py
affirm/model_interpretation/__init__.py
affirm/model_interpretation/shparkley/__init__.py
affirm/model_interpretation/shparkley/estimator_interface.py
affirm/model_interpretation/shparkley/spark_shapley.py
examples/__init__.py
examples/training_data_generator.py
tests/__init__.py
tests/examples/__init__.py
tests/examples/test_training_data_generator.py
tests/model_interpretation/__init__.py
tests/model_interpretation/shparkley/__init__.py
tests/model_interpretation/shparkley/test_estimator_interface.py
tests/model_interpretation/shparkley/test_spark_shapley.py
shparkley-1.0.1.dist-info/LICENSE
shparkley-1.0.1.dist-info/METADATA
shparkley-1.0.1.dist-info/WHEEL
shparkley-1.0.1.dist-info/top_level.txt
shparkley-1.0.1.dist-info/RECORD
