Metadata-Version: 2.1
Name: shparkley
Version: 1.0.1
Summary: Scaling Shapley Value computation using Spark
Home-page: https://github.com/Affirm/shparkley
Author: niloygupta, isaacjoseph
Author-email: niloy.gupta@affirm.com, isaac.c.joseph@gmail.com
License: UNKNOWN
Platform: UNKNOWN
Classifier: Programming Language :: Python :: 3
Classifier: License :: OSI Approved :: BSD License
Classifier: Operating System :: OS Independent
Requires-Python: >=3.6
Requires-Dist: future
Requires-Dist: mock
Requires-Dist: numpy
Requires-Dist: pyspark
